gaplint.py
gaplint-1.6.1.dist-info/licenses/LICENSE
gaplint-1.6.1.dist-info/METADATA
gaplint-1.6.1.dist-info/WHEEL
gaplint-1.6.1.dist-info/entry_points.txt
gaplint-1.6.1.dist-info/top_level.txt
gaplint-1.6.1.dist-info/RECORD
